danial_todo-0.1.0.dist-info/licenses/LICENSE
todo_evolution/__init__.py
todo_evolution/cli/__init__.py
todo_evolution/cli/commands.py
todo_evolution/cli/interactive.py
todo_evolution/cli/main.py
todo_evolution/cli/utils.py
todo_evolution/models/__init__.py
todo_evolution/models/task.py
todo_evolution/services/__init__.py
todo_evolution/services/task_service.py
danial_todo-0.1.0.dist-info/METADATA
danial_todo-0.1.0.dist-info/WHEEL
danial_todo-0.1.0.dist-info/entry_points.txt
danial_todo-0.1.0.dist-info/top_level.txt
danial_todo-0.1.0.dist-info/RECORD
