Metadata-Version: 2.4
Name: danial-todo
Version: 0.1.0
Summary: Professional in-memory Python console todo app with beautiful TUI
Author-email: Developer <developer@example.com>
License-Expression: MIT
Project-URL: Homepage, https://github.com/yourusername/todo-evolution
Project-URL: Repository, https://github.com/yourusername/todo-evolution
Project-URL: Issues, https://github.com/yourusername/todo-evolution/issues
Keywords: todo,cli,tui,task-management,console
Classifier: Development Status :: 3 - Alpha
Classifier: Intended Audience :: Developers
Classifier: Programming Language :: Python :: 3
Classifier: Programming Language :: Python :: 3.13
Classifier: Topic :: Software Development :: Libraries :: Python Modules
Classifier: Topic :: Utilities
Requires-Python: >=3.13
License-File: LICENSE
Requires-Dist: rich>=13.0.0
Requires-Dist: questionary>=2.0.0
Requires-Dist: pyfiglet>=1.0.0
Provides-Extra: dev
Requires-Dist: pytest>=8.0.0; extra == "dev"
Requires-Dist: pytest-cov>=4.0.0; extra == "dev"
Requires-Dist: black>=24.0.0; extra == "dev"
Requires-Dist: ruff>=0.1.0; extra == "dev"
Requires-Dist: mypy>=1.8.0; extra == "dev"
Dynamic: license-file
